academicdb/__about__.py
academicdb/__init__.py
academicdb/coauthor_setup.py
academicdb/crossref_utils.py
academicdb/database.py
academicdb/dbbuilder.py
academicdb/fix_conference_file.py
academicdb/get_collaborators.py
academicdb/nsf_collaborators.csv
academicdb/orcid.py
academicdb/publication.py
academicdb/publication_utils.py
academicdb/pubmed.py
academicdb/query.py
academicdb/recordConverter.py
academicdb/render_cv.py
academicdb/render_pubs.py
academicdb/researcher.py
academicdb/utils.py
academicdb/data/__init__.py
academicdb/data/latex_footer.tex
academicdb/data/latex_header.tex
academicdb-0.2.1.dist-info/METADATA
academicdb-0.2.1.dist-info/WHEEL
academicdb-0.2.1.dist-info/entry_points.txt
academicdb-0.2.1.dist-info/licenses/LICENSE
academicdb-0.2.1.dist-info/RECORD
