Metadata-Version: 2.4
Name: academicdb
Version: 0.2.1
Summary: Database for an academic CV
Author-email: Russ Poldrack <poldrack@gmail.com>
License-File: LICENSE
Requires-Python: >=3.12
Requires-Dist: biopython>=1.84
Requires-Dist: crossrefapi>=1.6.0
Requires-Dist: ipython>=8.31.0
Requires-Dist: matplotlib>=3.10.0
Requires-Dist: numpy>=2.2.1
Requires-Dist: orcid>=1.0.3
Requires-Dist: pandas>=2.2.3
Requires-Dist: pybliometrics>=4.1
Requires-Dist: pymongo>=4.10.1
Requires-Dist: pytest>=8.3.4
Requires-Dist: scholarly>=1.7.11
Requires-Dist: toml>=0.10.2
Requires-Dist: tomli-w>=1.1.0
Requires-Dist: tomli>=2.2.1
